crawl4ai_mcp/__init__.py
crawl4ai_mcp/__main__.py
crawl4ai_mcp/event_store.py
crawl4ai_mcp/server.py
crawl4ai_mcp/config/__init__.py
crawl4ai_mcp/config/settings.py
crawl4ai_mcp/handles/__init__.py
crawl4ai_mcp/handles/base.py
crawl4ai_mcp/handles/crawl4ai_ask.py
crawl4ai_mcp/handles/crawl4ai_crawl.py
crawl4ai_mcp/handles/crawl4ai_execute_js.py
crawl4ai_mcp/handles/crawl4ai_html.py
crawl4ai_mcp/handles/crawl4ai_md.py
crawl4ai_mcp/handles/crawl4ai_pdf.py
crawl4ai_mcp/handles/crawl4ai_screenshot.py
crawl4ai_mcp_sse_stdio-1.1.0.dist-info/licenses/LICENSE
crawl4ai_mcp_sse_stdio-1.1.0.dist-info/METADATA
crawl4ai_mcp_sse_stdio-1.1.0.dist-info/WHEEL
crawl4ai_mcp_sse_stdio-1.1.0.dist-info/entry_points.txt
crawl4ai_mcp_sse_stdio-1.1.0.dist-info/top_level.txt
crawl4ai_mcp_sse_stdio-1.1.0.dist-info/RECORD
