Metadata-Version: 2.4
Name: crawl4ai-mcp-sse-stdio
Version: 1.1.0
Summary: MCP (Model Context Protocol) server for Crawl4AI - Universal web crawling and data extraction
Author: stgmt
License: MIT
Project-URL: Homepage, https://github.com/stgmt/crawl4ai-mcp
Project-URL: Documentation, https://github.com/stgmt/crawl4ai-mcp#readme
Project-URL: Repository, https://github.com/stgmt/crawl4ai-mcp
Project-URL: Issues, https://github.com/stgmt/crawl4ai-mcp/issues
Keywords: mcp,model-context-protocol,crawl4ai,web-scraping,web-crawler,data-extraction,ai-tools,llm-tools,anthropic,claude,openai,chatgpt,async,python,sse,server-sent-events,stdio,http,webscraping,beautifulsoup,playwright,selenium,api,automation
Classifier: Development Status :: 4 - Beta
Classifier: Intended Audience :: Developers
Classifier: Topic :: Software Development :: Libraries :: Python Modules
Classifier: Topic :: Internet :: WWW/HTTP :: Dynamic Content
Classifier: Topic :: Scientific/Engineering :: Artificial Intelligence
Classifier: License :: OSI Approved :: MIT License
Classifier: Programming Language :: Python :: 3
Classifier: Programming Language :: Python :: 3.9
Classifier: Programming Language :: Python :: 3.10
Classifier: Programming Language :: Python :: 3.11
Classifier: Programming Language :: Python :: 3.12
Classifier: Operating System :: OS Independent
Requires-Python: >=3.10
License-File: LICENSE
Requires-Dist: mcp>=1.0.0
Requires-Dist: crawl4ai>=0.2.0
Requires-Dist: starlette>=0.27.0
Requires-Dist: uvicorn[standard]>=0.24.0
Requires-Dist: httpx>=0.25.0
Requires-Dist: pydantic>=2.0.0
Requires-Dist: python-dotenv>=1.0.0
Requires-Dist: typing-extensions>=4.0.0
Requires-Dist: aiofiles>=23.0.0
Provides-Extra: dev
Requires-Dist: pytest>=7.0.0; extra == "dev"
Requires-Dist: pytest-asyncio>=0.21.0; extra == "dev"
Requires-Dist: pytest-cov>=4.0.0; extra == "dev"
Requires-Dist: black>=23.0.0; extra == "dev"
Requires-Dist: mypy>=1.0.0; extra == "dev"
Requires-Dist: ruff>=0.1.0; extra == "dev"
Requires-Dist: pre-commit>=3.0.0; extra == "dev"
Provides-Extra: test
Requires-Dist: pytest>=7.0.0; extra == "test"
Requires-Dist: pytest-asyncio>=0.21.0; extra == "test"
Requires-Dist: pytest-cov>=4.0.0; extra == "test"
Requires-Dist: pytest-mock>=3.10.0; extra == "test"
Requires-Dist: httpx>=0.25.0; extra == "test"
Dynamic: license-file
